xlsxmetadata
