Metadata-Version: 2.1
Name: xlsxmetadata
Version: 0.0.2
Summary: Really lightweight lib for peeking into xlsx column/row size before you try to open the file with something else
Home-page: https://github.com/automatonymous/xlsxmetadata
Author: automatonymous
Author-email: spmassot@gmail.com
License: UNKNOWN
Platform: UNKNOWN
